progressor.py
python_progressor-0.2.0.dist-info/WHEEL
python_progressor-0.2.0.dist-info/METADATA
python_progressor-0.2.0.dist-info/RECORD
