Metadata-Version: 2.1
Name: python-progressor
Version: 0.2.0
Summary: A client library to Progressor server, able to track multiple progress bars simultaneously.
Home-page: https://github.com/40ants/python-progressor
Keywords: progress,bar,long,running,processes
Author: Alexander Artemenko
Author-email: svetlyak.40wt@gmail.com
Requires-Python: >=2.7, !=3.0.*, !=3.1.*, !=3.2.*, !=3.3.*, !=3.4.*, !=3.5.*
Classifier: Programming Language :: Python :: 2
Classifier: Programming Language :: Python :: 2.7
Classifier: Programming Language :: Python :: 3
Classifier: Programming Language :: Python :: 3.6
Classifier: Programming Language :: Python :: 3.7
Requires-Dist: jsonrpc-requests (>=0.4.0,<0.5.0)
Project-URL: Repository, https://github.com/40ants/python-progressor
